DB/Initializer.py
DB/__init__.py
DB/connection.py
config/__init__.py
config/config.py
config/logging_conf.py
extract/__init__.py
extract/json_extractor.py
load/__init__.py
load/incremental_loader.py
load/staging_loader.py
parsing/__init__.py
parsing/chamber_parser.py
parsing/notar_parser.py
parsing/person_parser.py
parsing/relationships_parser.py
transform/__init__.py
transform/address_normalizer.py
transform/cleaning.py
transform/combine_gender.py
transform/date_transformer.py
transform/gender_parsing_trasnformer.py
transform/hash_generator.py
transform/id_generator.py
transform/phone_normalizer.py
transform/transform_pipeline.py
transform/url_transformer.py
custom_etl_pipeline-0.1.1.dist-info/METADATA
custom_etl_pipeline-0.1.1.dist-info/WHEEL
custom_etl_pipeline-0.1.1.dist-info/top_level.txt
custom_etl_pipeline-0.1.1.dist-info/RECORD
